{"base_language": "spa", "action_sets": [{"y": 0, "x": 100, "destination": "f7f47432-acf6-4163-9528-af4ae9081fa2", "uuid": "9e306661-57d7-47ec-8d0c-20d01285df2d", "actions": [{"msg": {"spa": "Dale a tu bebe papillas a partir de la proxima semana. Necesitaras un vaso o plato, una cucharita limpia. Sabes que alimentos darle? (Si/No)"}, "media": {}, "send_all": false, "type": "reply"}]}, {"y": 373, "x": 494, "destination": null, "uuid": "85abece5-96e3-49a1-b339-1d138aab4005", "actions": [{"msg": {"spa": "Disculpa, no te entendi. Necesitaras un vaso o plato, una cucharita limpia. Sabes que alimentos darle? (Si/No)"}, "media": {}, "send_all": false, "type": "reply"}]}, {"y": 556, "x": 52, "destination": null, "uuid": "2f35a11e-f810-49f8-a767-f9e5c4ce314d", "actions": [{"msg": {"spa": "De acuerdo.\u00a0La proxima semana tu bebe podra comer papillas. Dale una pequena porcion de pure de fruta, vegetales o atole 2-3 veces al dia."}, "media": {}, "send_all": false, "type": "reply"}]}, {"y": 621, "x": 336, "destination": null, "uuid": "f1e48298-bb42-4bb8-b794-1c797c553990", "actions": [{"msg": {"spa": "A partir de la proxima semana tu bebe podra comer papillas. Dale una pequena porcion de pure de fruta, vegetales o atole 2-3 veces al dia."}, "media": {}, "send_all": false, "type": "reply"}]}], "version": 10, "flow_type": "F", "entry": "9e306661-57d7-47ec-8d0c-20d01285df2d", "rule_sets": [{"uuid": "f7f47432-acf6-4163-9528-af4ae9081fa2", "rules": [{"test": {"test": {"spa": "si s sip"}, "type": "contains_any"}, "category": {"spa": "Si"}, "destination": "2f35a11e-f810-49f8-a767-f9e5c4ce314d", "uuid": "6b403ab1-8ae6-4075-ac0d-95455cedaecd", "destination_type": "A"}, {"test": {"test": {"spa": "no n nop"}, "type": "contains_any"}, "category": {"spa": "No"}, "destination": "f1e48298-bb42-4bb8-b794-1c797c553990", "uuid": "d0cf3231-6567-4283-a27e-245de1fc219a", "destination_type": "A"}, {"test": {"test": "true", "type": "true"}, "category": {"spa": "Other"}, "destination": "85abece5-96e3-49a1-b339-1d138aab4005", "uuid": "f0af22fa-a7c8-4531-9894-5ac73ea056ef", "destination_type": "A"}], "ruleset_type": "wait_message", "label": "Response 1", "y": 301, "finished_key": null, "response_type": "", "operand": "@step.value", "x": 135, "config": {}}], "metadata": {"expires": 10080, "saved_on": "2017-04-13T19:37:10.670104Z", "uuid": "1abd462b-b777-4e84-97f0-d78093575416", "name": "b_nutrition_cSE_w26_d2", "revision": 9}}