{"base_language": "spa", "action_sets": [{"y": 0, "x": 100, "destination": "5d8996f7-c09d-4721-bc27-154122727ff5", "uuid": "ae826e8b-0d80-4c57-ab55-1431a79b25e1", "actions": [{"msg": {"spa": "Amamantar al bebe lo protegera de diarrea. Tambien lavarse las manos antes de tocarlo. Tu y tu familia se lavan las manos con jabon de forma regular?"}, "type": "reply"}]}, {"y": 171, "x": 470, "destination": "5d8996f7-c09d-4721-bc27-154122727ff5", "uuid": "f86983a3-61c4-4291-bc07-c4f1f1fe3ccd", "actions": [{"msg": {"spa": "Disculpa, no te entendi. Tu y tu familia se lavan las manos con jabon de forma regular?"}, "type": "reply"}]}, {"y": 394, "x": 7, "destination": null, "uuid": "d1c071a6-caef-495d-813d-33e5c3a37e34", "actions": [{"msg": {"spa": "De acuerdo. Lavarse las manos siempre, despues de ir al bano o cambiar panales o antes de cocinar y comer, ayuda a que tu y tu familia esten saludables."}, "type": "reply"}]}, {"y": 391, "x": 263, "destination": null, "uuid": "7b80ffe3-b761-436b-be79-3862b8d6566a", "actions": [{"msg": {"spa": "Lavarte las manos siempre, despues de ir al bano o cambiar panales o antes de cocinar y comer, ayuda a que tu y tu familia esten saludables"}, "type": "reply"}]}], "version": 10, "flow_type": "F", "entry": "ae826e8b-0d80-4c57-ab55-1431a79b25e1", "rule_sets": [{"uuid": "5d8996f7-c09d-4721-bc27-154122727ff5", "rules": [{"test": {"test": {"spa": "si s sip"}, "type": "contains_any"}, "category": {"spa": "Si"}, "destination": "d1c071a6-caef-495d-813d-33e5c3a37e34", "uuid": "598bf620-f9fa-410b-9e29-e61183765fa5", "destination_type": "A"}, {"test": {"test": {"spa": "no n nop"}, "type": "contains_any"}, "category": {"spa": "No"}, "destination": "7b80ffe3-b761-436b-be79-3862b8d6566a", "uuid": "122aaa30-2b2a-4efb-9386-d6589bf64015", "destination_type": "A"}, {"test": {"test": "true", "type": "true"}, "category": {"spa": "Other"}, "destination": "f86983a3-61c4-4291-bc07-c4f1f1fe3ccd", "uuid": "985eb189-ada8-4ba3-97c2-75ff799f57b1", "destination_type": "A"}], "ruleset_type": "wait_message", "label": "Response 1", "y": 229, "finished_key": null, "response_type": "", "operand": "@step.value", "x": 92, "config": {}}], "metadata": {"expires": 10080, "saved_on": "2017-01-10T15:39:09.086323Z", "uuid": "217e065e-31d1-46fc-926d-073968cc86b6", "name": "b_prevent_cSE_w3_d4", "revision": 12}}