{"base_language": "spa", "action_sets": [{"y": 0, "x": 100, "destination": null, "uuid": "300381a4-e64a-48f9-a6b4-3058407bebaa", "actions": [{"msg": {"spa": "Reto semanal: @contact.rp_name\u00a0 crees poderte comer una pieza de fruta cada dia de esta semana? Intenta comer una fruta distinta cada dia!"}, "type": "reply"}]}], "version": 10, "flow_type": "F", "entry": "300381a4-e64a-48f9-a6b4-3058407bebaa", "rule_sets": [], "metadata": {"expires": 10080, "saved_on": "2017-01-05T15:52:34.788872Z", "uuid": "294c144a-a622-4cac-bdce-403edc4e918a", "name": "p_reto_w10_d2", "revision": 1}}