{"base_language": "spa", "action_sets": [{"y": 0, "x": 100, "destination": null, "uuid": "e46c58a3-a2f1-424c-8501-390a58e27e30", "actions": [{"msg": {"spa": "Recuerda que no debes fumar o tomar alcohol. Puede danar a tu bebe y su crecimiento. Si sientes que necesitas apoyo no dudes en pedirlo. Ve a tu unidad clinica."}, "type": "reply"}]}], "version": 10, "flow_type": "F", "entry": "e46c58a3-a2f1-424c-8501-390a58e27e30", "rule_sets": [], "metadata": {"expires": 4320, "saved_on": "2016-12-20T18:26:57.911386Z", "uuid": "29caf16d-cb37-4e7c-b254-a2ebe0a69a08", "name": "p_prevent_w31_d5", "revision": 1}}