{"base_language": "spa", "action_sets": [{"y": 0, "x": 100, "destination": null, "uuid": "5c12a9db-0517-4a00-8732-dd1d6579bcf8", "actions": [{"msg": {"spa": "Tu bebe ya puede tener algo de pelo! Pronto estara listo para nacer. Recuerda tu plan de seguridad y ten dinero guardado listo para el gran momento."}, "type": "reply"}]}], "version": 10, "flow_type": "F", "entry": "5c12a9db-0517-4a00-8732-dd1d6579bcf8", "rule_sets": [], "metadata": {"expires": 4320, "saved_on": "2016-12-20T18:29:11.755195Z", "uuid": "531eb465-3783-41b8-ae90-7d9c3b1b6003", "name": "p_development_w32_d1", "revision": 1}}