{"base_language": "spa", "action_sets": [{"y": 0, "x": 100, "destination": null, "uuid": "0e2f08ec-9689-4fe4-96c3-51ee3f147ef6", "actions": [{"msg": {"spa": "Si tu hijo(a) se porta mal, piensa en como se comporta la familia a su alrededor. Los ninos siguen los habitos de la familia y los copian."}, "media": {}, "send_all": false, "type": "reply"}]}], "version": 10, "flow_type": "F", "entry": "0e2f08ec-9689-4fe4-96c3-51ee3f147ef6", "rule_sets": [], "metadata": {"expires": 10080, "saved_on": "2017-04-17T19:14:12.163912Z", "uuid": "7323d7cd-468c-4118-97d6-ad6da6ae13e9", "name": "b_development_w95_d5", "revision": 1}}