{"base_language": "spa", "action_sets": [{"y": 0, "x": 100, "destination": "aeef7623-8ba6-45e9-9235-26b38df3581c", "uuid": "78c58482-fd53-4c2c-83b9-d84dd96403c9", "actions": [{"msg": {"spa": "Me gustaria saber como te fue en tu cita a los 7 dias del parto.Te revisaron a ti en el centro de salud? (Si/No)"}, "type": "reply"}]}, {"y": 469, "x": 0, "destination": null, "uuid": "ca66d8a3-3682-4a13-87c0-0300cd891ac6", "actions": [{"msg": {"spa": "De acuerdo. Trata de descansar  y comer bien para recuperarte."}, "type": "reply"}]}, {"y": 446, "x": 242, "destination": null, "uuid": "1fb0c19d-23d1-4be3-a662-e072dbf5eaf2", "actions": [{"msg": {"spa": "Tu doctor necesita asegurarse de que te estes recuperando adecuadamente. Es importante que vayas lo mas pronto posible."}, "type": "reply"}]}, {"y": 229, "x": 453, "destination": "aeef7623-8ba6-45e9-9235-26b38df3581c", "uuid": "b8d28704-b31f-4667-9064-2fd37463b684", "actions": [{"msg": {"spa": "Disculpa, no te entendi. Me gustaria saber como te fue en tu cita a los 7 dias del parto. Te revisaron a ti en el centro de salud? (Si/No)"}, "type": "reply"}]}], "version": 10, "flow_type": "F", "entry": "78c58482-fd53-4c2c-83b9-d84dd96403c9", "rule_sets": [{"uuid": "aeef7623-8ba6-45e9-9235-26b38df3581c", "rules": [{"test": {"test": {"spa": "si s sip"}, "type": "contains_any"}, "category": {"spa": "Si"}, "destination": "ca66d8a3-3682-4a13-87c0-0300cd891ac6", "uuid": "d676f188-2fa3-49bc-acea-9ef77ff3e0d7", "destination_type": "A"}, {"test": {"test": {"spa": "no n nop"}, "type": "contains_any"}, "category": {"spa": "No"}, "destination": "1fb0c19d-23d1-4be3-a662-e072dbf5eaf2", "uuid": "bd360c95-89f9-4165-9964-edcaffadf0e1", "destination_type": "A"}, {"test": {"test": "true", "type": "true"}, "category": {"spa": "Other"}, "destination": "b8d28704-b31f-4667-9064-2fd37463b684", "uuid": "0a2df501-b89f-4e1b-9e10-81f8f21a91f8", "destination_type": "A"}], "ruleset_type": "wait_message", "label": "Response 1", "y": 246, "finished_key": null, "response_type": "", "operand": "@step.value", "x": 127, "config": {}}], "metadata": {"expires": 4320, "saved_on": "2017-01-10T15:34:01.325699Z", "uuid": "7a6530e1-1cfc-441a-a1b5-dc1162a4b074", "name": "b_reminders_cSE_w2_d5", "revision": 14}}