{"base_language": "spa", "action_sets": [{"y": 42, "x": 500, "destination": "a80632c9-4dd4-4000-aeff-a9aec821a90a", "uuid": "ed01d010-d1f8-492c-a078-3a902821847b", "actions": [{"msg": {"spa": "Hola @contact.rp_name  ! Ya nacio tu bebe? (Si/No)"}, "type": "reply"}]}, {"y": 559, "x": 499, "destination": null, "uuid": "139933ed-8e95-4cda-a450-b287f63eed85", "actions": [{"msg": {"spa": "Ve a tu centro de salud u hospital de inmediato y diles que aun no ha nacido tu bebe. Todo estara bien pero es tiempo de que vayas o llames al 018006283762."}, "type": "reply"}]}, {"y": 140, "x": 789, "destination": "a80632c9-4dd4-4000-aeff-a9aec821a90a", "uuid": "ec98f476-1f26-4233-babc-7cb53ae5c318", "actions": [{"msg": {"spa": "Disculpa, no entendi. Ya nacio tu bebe? (Si/No)"}, "type": "reply"}]}, {"y": 360, "x": 162, "destination": null, "uuid": "5b8e9a04-1994-4c52-9157-305dbb552a59", "actions": [{"flow": {"name": "birth", "uuid": "fb7d0fcb-5887-4031-bf1a-ef60a74158b8"}, "type": "flow"}]}], "version": 10, "flow_type": "F", "entry": "ed01d010-d1f8-492c-a078-3a902821847b", "rule_sets": [{"uuid": "a80632c9-4dd4-4000-aeff-a9aec821a90a", "rules": [{"test": {"test": {"spa": "s"}, "type": "starts"}, "category": {"spa": "Si", "base": "Si"}, "destination": "5b8e9a04-1994-4c52-9157-305dbb552a59", "uuid": "d9315336-ffc2-4366-8f2b-0951784fefdb", "destination_type": "A"}, {"test": {"test": {"spa": "n"}, "type": "starts"}, "category": {"spa": "No", "base": "No"}, "destination": "139933ed-8e95-4cda-a450-b287f63eed85", "uuid": "8483dcfc-d76b-42d3-9f7c-e3042bfbe281", "destination_type": "A"}, {"test": {"test": "true", "type": "true"}, "category": {"spa": "Other", "base": "All Responses"}, "destination": "ec98f476-1f26-4233-babc-7cb53ae5c318", "uuid": "bc1af1d1-8fbe-43ff-8148-195f2f95254b", "destination_type": "A"}], "ruleset_type": "wait_message", "label": "Response 1_s", "y": 233, "finished_key": null, "response_type": "", "operand": "@step.value", "x": 465, "config": {}}], "metadata": {"uuid": "8c425746-9919-4cae-95e7-a5b703619475", "notes": [], "expires": 10080, "name": "concerns18", "saved_on": "2016-08-21T23:12:08.770275Z", "revision": 69}}