{"base_language": "spa", "action_sets": [{"y": 0, "x": 100, "destination": null, "uuid": "2e87e315-5cf4-4f6a-8fde-3bcbb9307160", "actions": [{"msg": {"spa": "Lava las frutas y verduras antes de darselas a tu bebe.Esto les quita la tierra y germenes.  Coce bien alimentos de origen animal y conservalos frescos."}, "media": {}, "send_all": false, "type": "reply"}]}], "version": 10, "flow_type": "F", "entry": "2e87e315-5cf4-4f6a-8fde-3bcbb9307160", "rule_sets": [], "metadata": {"expires": 10080, "saved_on": "2017-04-17T17:04:49.184815Z", "uuid": "9ab88b4e-5e68-4ff1-aefa-aa8b1c16c9c5", "name": "b_prevent_w74_d2", "revision": 1}}