{"base_language": "spa", "action_sets": [{"y": 0, "x": 494, "destination": "d5eb4de7-cb3f-496a-b2d2-c34cb11c5196", "uuid": "2d4d4b14-e573-4a54-b59a-61e4da6a5161", "actions": [{"msg": {"spa": "Has sentido que tu panza se pone dura de repente y luego se relaja? (Si/No)"}, "type": "reply"}]}, {"y": 395, "x": 340, "destination": null, "uuid": "8cc79a6e-43ef-4e33-91cf-380954f91a63", "actions": [{"msg": {"spa": "No hay nada de que preocuparse. Esta es solo una contraccion de practica. Tu cuerpo se va preparando para la labor de parto."}, "type": "reply"}]}, {"y": 392, "x": 564, "destination": null, "uuid": "5cb12859-8c29-4546-b9a2-8613832fd601", "actions": [{"msg": {"spa": "Si llegas a sentirlo, no hay nada de que preocuparse. Esta es solo una contraccion de practica. Tu cuerpo se va preparando para la labor de parto."}, "type": "reply"}]}, {"y": 99, "x": 784, "destination": "d5eb4de7-cb3f-496a-b2d2-c34cb11c5196", "uuid": "7bbedd40-4f14-4716-b926-ab659dfff487", "actions": [{"msg": {"spa": "Disculpa, no pude comprender. Has sentido que tu panza se pone dura de repente y luego se relaja? (Si/No)"}, "type": "reply"}]}], "version": 10, "flow_type": "F", "entry": "2d4d4b14-e573-4a54-b59a-61e4da6a5161", "rule_sets": [{"uuid": "d5eb4de7-cb3f-496a-b2d2-c34cb11c5196", "rules": [{"test": {"test": {"spa": "s"}, "type": "starts"}, "category": {"spa": "Si", "base": "Si"}, "destination": "8cc79a6e-43ef-4e33-91cf-380954f91a63", "uuid": "2e88e4df-3ee7-45dd-b713-2bf72e2c0b6a", "destination_type": "A"}, {"test": {"test": {"spa": "n"}, "type": "starts"}, "category": {"spa": "No", "base": "No"}, "destination": "5cb12859-8c29-4546-b9a2-8613832fd601", "uuid": "fe965363-b15f-4713-bf2f-b600b788b41c", "destination_type": "A"}, {"test": {"test": "true", "type": "true"}, "category": {"spa": "Other", "base": "All Responses"}, "destination": "7bbedd40-4f14-4716-b926-ab659dfff487", "uuid": "a20cc287-90e4-4fba-ad05-a1f8e3929582", "destination_type": "A"}], "ruleset_type": "wait_message", "label": "Response 1_s", "y": 240, "finished_key": null, "response_type": "", "operand": "@step.value", "x": 461, "config": {}}], "metadata": {"expires": 10080, "revision": 11, "uuid": "e7822a7c-f201-4d51-8277-3e46f72942f1", "name": "concerns12", "saved_on": "2016-08-21T23:03:08.780274Z"}}