{"base_language": "spa", "action_sets": [{"y": 0, "x": 100, "destination": "ef5e67ee-d368-4f84-af20-a8e670c2f2fc", "uuid": "4d2e789a-8929-4e98-bfb2-4a09f4d533ee", "actions": [{"msg": {"spa": "Queremos hacerte dos preguntas rapidas sobre tu ultima consulta para poder mejorar el servicio de tu centro de salud."}, "type": "reply"}, {"msg": {"spa": "Tu opinion sincera de los servicios de salud es muy importante para poder mejorarlos. Nadie sabra lo que contestes: es anonimo."}, "type": "reply"}, {"msg": {"spa": "Primera pregunta, en tu ultima cita te preguntaron o dieron consejos sobre tu estado de \u00e1nimo? Si/No"}, "type": "reply"}]}, {"y": 413, "x": 463, "destination": "ef5e67ee-d368-4f84-af20-a8e670c2f2fc", "uuid": "5831d746-4918-4b93-8a25-9779a2c71a1e", "actions": [{"msg": {"spa": "Disculpa, no te entendi. En tu ultima cita te preguntaron o dieron consejos sobre tu estado de \u00e1nimo? Si/No"}, "type": "reply"}]}, {"y": 724, "x": 102, "destination": "aaffb781-7366-43d4-ae35-29db166e958d", "uuid": "ec5697ba-6911-4a84-98fc-f4c62fbeaaf3", "actions": [{"msg": {"spa": "Finalmente, que tan contenta estas con la cantidad de tiempo que te dedicaron el doctor y enfermera en tu consulta? (1-4) 1 es nada contenta y 4 es muy contenta"}, "type": "reply"}]}, {"y": 788, "x": 550, "destination": "aaffb781-7366-43d4-ae35-29db166e958d", "uuid": "5fc87f0b-81c0-42b8-95ad-e53a7e1476b1", "actions": [{"msg": {"spa": "No entendi. Que tan contenta estas con la cantidad de tiempo que te dedicaron el doctor y enfermera en tu consulta? (1-4) 1 es nada contenta y 4 es muy contenta"}, "type": "reply"}]}, {"y": 1308, "x": 177, "destination": null, "uuid": "acbc93b3-5c2e-4baa-9a40-06f3d6b82401", "actions": [{"msg": {"spa": "Gracias por tu opinion! La utilizaremos, junto con la de otras mamas como tu, para revisar el desempeno del personal de salud y el servicio de tu clinica."}, "type": "reply"}]}], "version": 10, "flow_type": "F", "entry": "4d2e789a-8929-4e98-bfb2-4a09f4d533ee", "rule_sets": [{"uuid": "ef5e67ee-d368-4f84-af20-a8e670c2f2fc", "rules": [{"test": {"test": {"spa": "si s sip"}, "type": "contains_any"}, "category": {"spa": "Si"}, "destination": "ec5697ba-6911-4a84-98fc-f4c62fbeaaf3", "uuid": "be80e58b-65a5-4919-8200-0347b37c6f09", "destination_type": "A"}, {"test": {"test": {"spa": "no n nop"}, "type": "contains_any"}, "category": {"spa": "No"}, "destination": "ec5697ba-6911-4a84-98fc-f4c62fbeaaf3", "uuid": "f2ea2867-4899-441a-9a33-c62ed0aeacc3", "destination_type": "A"}, {"test": {"test": "true", "type": "true"}, "category": {"spa": "Other"}, "destination": "5831d746-4918-4b93-8a25-9779a2c71a1e", "uuid": "4b6fa3f5-37de-4017-92e0-ea0cbe80c0d3", "destination_type": "A"}], "ruleset_type": "wait_message", "label": "Response 1", "y": 529, "finished_key": null, "response_type": "", "operand": "@step.value", "x": 123, "config": {}}, {"uuid": "aaffb781-7366-43d4-ae35-29db166e958d", "rules": [{"test": {"test": "1", "type": "eq"}, "category": {"spa": "1"}, "destination": "acbc93b3-5c2e-4baa-9a40-06f3d6b82401", "uuid": "78762f9b-be8b-4f16-96d1-e198e28c8e58", "destination_type": "A"}, {"test": {"test": "2", "type": "eq"}, "category": {"spa": "2"}, "destination": "acbc93b3-5c2e-4baa-9a40-06f3d6b82401", "uuid": "b99139a8-8dc4-4cec-8239-f47fda4d1499", "destination_type": "A"}, {"test": {"test": "3", "type": "eq"}, "category": {"spa": "3"}, "destination": "acbc93b3-5c2e-4baa-9a40-06f3d6b82401", "uuid": "f67bb7a7-b2df-4535-b81f-8d0ed2184717", "destination_type": "A"}, {"test": {"test": "4", "type": "eq"}, "category": {"spa": "4"}, "destination": "acbc93b3-5c2e-4baa-9a40-06f3d6b82401", "uuid": "4dfeb45c-065d-4b9f-af81-30abf2d30810", "destination_type": "A"}, {"test": {"test": "true", "type": "true"}, "category": {"spa": "Other"}, "destination": "5fc87f0b-81c0-42b8-95ad-e53a7e1476b1", "uuid": "e24fd76d-4790-4376-a170-1896b665291a", "destination_type": "A"}], "ruleset_type": "wait_message", "label": "Response 2", "y": 976, "finished_key": null, "response_type": "", "operand": "@step.value", "x": 91, "config": {}}], "metadata": {"expires": 4320, "saved_on": "2016-12-29T19:27:30.005311Z", "uuid": "f418a10b-fade-4603-9155-1b54897dd9d5", "name": "b_incentives_w5_d3", "revision": 24}}